rfcommands/__init__.py
rfcommands/_version.py
rfcommands/bt2_log_to_csv.py
rfcommands/compile_step_stats.py
rfcommands/deduplicate.py
rfcommands/stats_percentage.py
rfcommands/sum_stats.py
rfcommands/cli/__init__.py
rfcommands/cli/bt2_log_to_csv.py
rfcommands/cli/compile_step_stats.py
rfcommands/cli/dedup.py
rfcommands/cli/main.py
rfcommands/cli/merge.py
rfcommands/cli/stats_percentage.py
rfcommands/cli/sum_stats.py
rfcommands/merge/__init__.py
rfcommands/merge/bowtie2_logs.py
rfcommands/merge/overall_stats.py
rfcommands-0.0.0.dist-info/LICENSE
rfcommands-0.0.0.dist-info/METADATA
rfcommands-0.0.0.dist-info/WHEEL
rfcommands-0.0.0.dist-info/entry_points.txt
rfcommands-0.0.0.dist-info/top_level.txt
rfcommands-0.0.0.dist-info/RECORD
